{
    "document_info": {
        "source_file": "Folder_HF_Enraizamento.pdf",
        "total_pages": 4,
        "processed_at": "2026-04-30 10:30:08"
    },
    "pages": [
        {
            "page_number": 0,
            "text_markdown": "**==> picture [613 x 859] intentionally omitted <==**\n\n",
            "metadata": {
                "format": "PDF 1.6",
                "title": "Folder_HF_Enraizamento",
                "author": "",
                "subject": "",
                "keywords": "",
                "creator": "Adobe Illustrator 29.6 (Windows)",
                "producer": "Adobe PDF library 17.00",
                "creationDate": "D:20250620125033-02'00'",
                "modDate": "D:20250620130222-03'00'",
                "trapped": "",
                "encryption": null,
                "file_path": "Folder_HF_Enraizamento.pdf",
                "page_count": 4,
                "page_number": 1
            }
        },
        {
            "page_number": 0,
            "text_markdown": "**==> picture [613 x 860] intentionally omitted <==**\n\n",
            "metadata": {
                "format": "PDF 1.6",
                "title": "Folder_HF_Enraizamento",
                "author": "",
                "subject": "",
                "keywords": "",
                "creator": "Adobe Illustrator 29.6 (Windows)",
                "producer": "Adobe PDF library 17.00",
                "creationDate": "D:20250620125033-02'00'",
                "modDate": "D:20250620130222-03'00'",
                "trapped": "",
                "encryption": null,
                "file_path": "Folder_HF_Enraizamento.pdf",
                "page_count": 4,
                "page_number": 2
            }
        },
        {
            "page_number": 0,
            "text_markdown": "**==> picture [613 x 860] intentionally omitted <==**\n\n",
            "metadata": {
                "format": "PDF 1.6",
                "title": "Folder_HF_Enraizamento",
                "author": "",
                "subject": "",
                "keywords": "",
                "creator": "Adobe Illustrator 29.6 (Windows)",
                "producer": "Adobe PDF library 17.00",
                "creationDate": "D:20250620125033-02'00'",
                "modDate": "D:20250620130222-03'00'",
                "trapped": "",
                "encryption": null,
                "file_path": "Folder_HF_Enraizamento.pdf",
                "page_count": 4,
                "page_number": 3
            }
        },
        {
            "page_number": 0,
            "text_markdown": "**==> picture [613 x 860] intentionally omitted <==**\n\n",
            "metadata": {
                "format": "PDF 1.6",
                "title": "Folder_HF_Enraizamento",
                "author": "",
                "subject": "",
                "keywords": "",
                "creator": "Adobe Illustrator 29.6 (Windows)",
                "producer": "Adobe PDF library 17.00",
                "creationDate": "D:20250620125033-02'00'",
                "modDate": "D:20250620130222-03'00'",
                "trapped": "",
                "encryption": null,
                "file_path": "Folder_HF_Enraizamento.pdf",
                "page_count": 4,
                "page_number": 4
            }
        }
    ]
}